ytmusicheadless/__init__.py
yt_music_headless-0.1.1.dist-info/LICENSE
yt_music_headless-0.1.1.dist-info/METADATA
yt_music_headless-0.1.1.dist-info/WHEEL
yt_music_headless-0.1.1.dist-info/entry_points.txt
yt_music_headless-0.1.1.dist-info/top_level.txt
yt_music_headless-0.1.1.dist-info/RECORD
